base32_tiny/__init__.py
base32_tiny/decode.py
base32_tiny/encode.py
base32_tiny-0.1.3.dist-info/LICENSE
base32_tiny-0.1.3.dist-info/METADATA
base32_tiny-0.1.3.dist-info/WHEEL
base32_tiny-0.1.3.dist-info/RECORD
