Metadata-Version: 2.3
Name: base32_tiny
Version: 0.1.3
Summary: Base32 encoding/decoding,  RFC4648, RFC4648_HEX, Crockford
License: MIT
Author: wangshangwen
Author-email: shangwenwang20@gmail.com
Requires-Python: >=3.6
Classifier: License :: OSI Approved :: MIT License
Classifier: Programming Language :: Python :: 3
Classifier: Programming Language :: Python :: 3.6
Classifier: Programming Language :: Python :: 3.7
Classifier: Programming Language :: Python :: 3.8
Classifier: Programming Language :: Python :: 3.9
Classifier: Programming Language :: Python :: 3.10
Classifier: Programming Language :: Python :: 3.11
Classifier: Programming Language :: Python :: 3.12
Classifier: Programming Language :: Python :: 3.13
Project-URL: Homepage, https://github.com/189/base32
